TCdone/__init__.py
TCdone/ibtracs.py
tcdone-0.1.5.dist-info/licenses/LICENSE
tcdone-0.1.5.dist-info/METADATA
tcdone-0.1.5.dist-info/WHEEL
tcdone-0.1.5.dist-info/top_level.txt
tcdone-0.1.5.dist-info/RECORD
